instanceTuner/__init__.py
instanceTuner/instanceTuner.py
instanceTuner/operator.py
instanceTuner/set.py
instanceTuner/setInstance.py
instanceTuner-1.6.2.dist-info/LICENSE
instanceTuner-1.6.2.dist-info/METADATA
instanceTuner-1.6.2.dist-info/WHEEL
instanceTuner-1.6.2.dist-info/top_level.txt
instanceTuner-1.6.2.dist-info/RECORD
