Metadata-Version: 2.1
Name: instanceTuner
Version: 1.6.2
Summary: Set limited type instances and overload functions like Java in python
Home-page: https://github.com/codingaround/InstanceTuner.git
Author: codingaround
Author-email: codingaround90s@gmail.com
License: GNU
Platform: UNKNOWN
Classifier: License :: OSI Approved :: GNU Affero General Public License v3
Classifier: Programming Language :: Python :: 3
Classifier: Programming Language :: Python :: 3.9
Requires-Dist: CAImport
